typhonlint_threadsafe/__init__.py
typhonlint_threadsafe/main.py
typhonlint_threadsafe/prompts.py
typhonlint_threadsafe-2025.12.21130210.dist-info/METADATA
typhonlint_threadsafe-2025.12.21130210.dist-info/WHEEL
typhonlint_threadsafe-2025.12.21130210.dist-info/top_level.txt
typhonlint_threadsafe-2025.12.21130210.dist-info/RECORD
