Metadata-Version: 2.4
Name: typhonlint-threadsafe
Version: 2025.12.21130210
Summary: A new package that analyzes user-provided JavaScript code snippets to determine if they can run concurrently without conflicts or race conditions. It takes the code as text input and returns a structu
Author-email: typhonlint-threadsafe <hi@eugene.plus>
License: MIT
Project-URL: Homepage, https://github.com/chigwell/typhonlint-threadsafe
Requires-Python: >=3.9
Requires-Dist: langchain-llm7>=0.0.0
Requires-Dist: llmatch-messages>=0.0.0
Requires-Dist: langchain-core>=0.3.0
